generated/__init__.py
generated/signal_processor_pb2.py
generated/signal_processor_pb2_grpc.py
generated/api/signal_processor_pb2.py
generated/api/signal_processor_pb2_grpc.py
signal_fabric/__init__.py
signal_fabric/grpc_client.py
signal_fabric_client-0.1.29.dist-info/licenses/LICENSE
signal_fabric_client-0.1.29.dist-info/METADATA
signal_fabric_client-0.1.29.dist-info/WHEEL
signal_fabric_client-0.1.29.dist-info/top_level.txt
signal_fabric_client-0.1.29.dist-info/RECORD
