Metadata-Version: 2.4
Name: signal-fabric-client
Version: 0.1.29
Summary: Client library for Signal Fabric
Home-page: https://github.com/phasequant/signal-fabric
Author: PhaseQuant
Author-email: 
License: MIT
Project-URL: Homepage, https://github.com/phasequant/signal-fabric
Project-URL: Repository, https://github.com/phasequant/signal-fabric
Project-URL: Issues, https://github.com/phasequant/signal-fabric/issues
Keywords: signal-fabric,grpc,client,trading,signals,market-data
Classifier: Development Status :: 3 - Alpha
Classifier: Intended Audience :: Developers
Classifier: Intended Audience :: Financial and Insurance Industry
Classifier: License :: OSI Approved :: MIT License
Classifier: Operating System :: OS Independent
Classifier: Programming Language :: Python :: 3
Classifier: Programming Language :: Python :: 3.8
Classifier: Programming Language :: Python :: 3.9
Classifier: Programming Language :: Python :: 3.10
Classifier: Programming Language :: Python :: 3.11
Classifier: Programming Language :: Python :: 3.12
Classifier: Topic :: Software Development :: Libraries :: Python Modules
Classifier: Topic :: Office/Business :: Financial
Requires-Python: >=3.8
License-File: LICENSE
Requires-Dist: grpcio<1.68.0,>=1.62.0
Requires-Dist: protobuf<6.0.0,>=5.26.0
Provides-Extra: dev
Requires-Dist: grpcio-tools<1.68.0,>=1.67.0; extra == "dev"
Dynamic: home-page
Dynamic: license-file
Dynamic: requires-python
